find_buildout_root.py
aifactory_tools_find_buildout_root-0.0.2.dist-info/METADATA
aifactory_tools_find_buildout_root-0.0.2.dist-info/RECORD
aifactory_tools_find_buildout_root-0.0.2.dist-info/WHEEL
aifactory_tools_find_buildout_root-0.0.2.dist-info/entry_points.txt
aifactory_tools_find_buildout_root-0.0.2.dist-info/top_level.txt
